arachniclient/__init__.py
arachniclient-0.3.data/scripts/arachni-client
arachniclient-0.3.dist-info/LICENSE
arachniclient-0.3.dist-info/METADATA
arachniclient-0.3.dist-info/WHEEL
arachniclient-0.3.dist-info/top_level.txt
arachniclient-0.3.dist-info/RECORD
