Metadata-Version: 2.1
Name: arachniclient
Version: 0.3
Summary: REST API client for arachni.
Home-page: https://github.com/catatonicprime/arachniclient
Author: catatonicprime
Author-email: catatonicprime@gmail.com
License: UNKNOWN
Platform: UNKNOWN
Classifier: Programming Language :: Python :: 3
Classifier: License :: OSI Approved :: MIT License
Classifier: Operating System :: OS Independent
Requires-Dist: requests
